{
  "generator-jhipster": {
    "authenticationType": "jwt",
    "cacheProvider": "ehcache",
    "serverPort": "8081",
    "serviceDiscoveryType": "eureka",
    "skipUserManagement": true,
    "baseName": "talktomem1",
    "buildTool": "maven",
    "databaseType": "sql",
    "devDatabaseType": "h2Disk",
    "enableHibernateCache": true,
    "enableSwaggerCodegen": false,
    "enableTranslation": true,
    "jhiPrefix": "jhi",
    "languages": ["en"],
    "messageBroker": false,
    "prodDatabaseType": "mysql",
    "searchEngine": false,
    "skipClient": true,
    "testFrameworks": [],
    "websocket": false,
    "applicationType": "microservice",
    "packageName": "com.talktomem",
    "packageFolder": "com/talktomem",
    "jhipsterVersion": "7.0.1",
    "clientPackageManager": "npm",
    "dtoSuffix": "DTO",
    "entitySuffix": "",
    "reactive": false,
    "skipServer": false,
    "skipCheckLengthOfIdentifier": false,
    "skipFakeData": false,
    "blueprints": [],
    "otherModules": [],
    "pages": [],
    "clientFramework": "angularX",
    "clientTheme": "none",
    "clientThemeVariant": "",
    "withAdminUi": true,
    "nativeLanguage": "en",
    "creationTimestamp": 1618763968650,
    "jwtSecretKey": "NGE2YmIyOGRhODJhZjRhNjJkYTFmNmY1NDBhOTI3ZDRmOTJiMjdlNmQxZTA5NTRkZWNlYmY2N2VjODZiODRkOTk5OGZlMTc2NDZlMzdkN2FjZmYwYjFmZWY4ZWQyMzZhOGFlZDk5NGUxMGM0YmU5YWI0M2IxM2Y2YjZkZTExYjQ=",
    "entities": ["A", "B"],
    "lastLiquibaseTimestamp": 1618764088000
  }
}
